fast_to_sql/__init__.py
fast_to_sql/errors.py
fast_to_sql/fast_to_sql.py
fast_to_sql/utils/__init__.py
fast_to_sql/utils/utility_funs.py
fast_to_sql-2.3.0.dist-info/LICENSE
fast_to_sql-2.3.0.dist-info/METADATA
fast_to_sql-2.3.0.dist-info/WHEEL
fast_to_sql-2.3.0.dist-info/top_level.txt
fast_to_sql-2.3.0.dist-info/RECORD
