Metadata-Version: 2.1
Name: fast-to-sql
Version: 2.3.0
Summary: An improved way to upload pandas dataframes to Microsoft SQL Server.
Home-page: https://github.com/jdglaser/fast-to-sql
Author: Jarred Glaser
Author-email: jarred.glaser@gmail.com
License: License :: OSI Approved :: MIT License
Keywords: pandas,to_sql,fast,sql
Classifier: Development Status :: 5 - Production/Stable
Classifier: Intended Audience :: Developers
Classifier: Programming Language :: Python :: 3.8
Classifier: Programming Language :: Python :: 3.9
Classifier: Programming Language :: Python :: 3.10
Classifier: Programming Language :: Python :: 3.11
Classifier: Programming Language :: Python :: 3.12
Classifier: License :: OSI Approved :: MIT License
License-File: LICENSE
Requires-Dist: pandas
Requires-Dist: pyodbc
